pi_camera_capture/__init__.py
pi_camera_capture/app.py
pi_camera_capture/cam.py
pi_camera_capture/cli.py
pi_camera_capture/picamera_mock.py
pi_camera_capture-0.1.3.dist-info/LICENSE
pi_camera_capture-0.1.3.dist-info/METADATA
pi_camera_capture-0.1.3.dist-info/WHEEL
pi_camera_capture-0.1.3.dist-info/entry_points.txt
pi_camera_capture-0.1.3.dist-info/top_level.txt
pi_camera_capture-0.1.3.dist-info/RECORD
