Metadata-Version: 2.1
Name: pi-camera-capture
Version: 0.1.3
Summary: UNKNOWN
Home-page: UNKNOWN
License: UNKNOWN
Platform: UNKNOWN
Requires-Dist: fire
Requires-Dist: requests
Provides-Extra: test
Requires-Dist: pillow ; extra == 'test'
Requires-Dist: pylint ; extra == 'test'
Requires-Dist: pytest ; extra == 'test'
Requires-Dist: pytest-mock ; extra == 'test'
Requires-Dist: responses ; extra == 'test'
